schmovie/__init__.py
schmovie/movie.py
schmovie-1.0.0.dist-info/LICENCE.txt
schmovie-1.0.0.dist-info/METADATA
schmovie-1.0.0.dist-info/WHEEL
schmovie-1.0.0.dist-info/top_level.txt
schmovie-1.0.0.dist-info/RECORD
