Metadata-Version: 2.1
Name: schmovie
Version: 1.0.0
Summary: A Python library leveraging the OMDb API to fetch movie details based on user-provided titles. It also offers plot translation from English to Indonesian using googletrans.
Home-page: https://github.com/codewithwan/schmovie
Author: codewithwan
Author-email: <deezerxstore@gmail.com>
License: MIT
Keywords: SCH,OMDb
Classifier: Development Status :: 1 - Planning
License-File: LICENCE.txt
